README.rst
setup.py
pmorse/Pmorse.py
pmorse/__init__.py
pmorse.egg-info/PKG-INFO
pmorse.egg-info/SOURCES.txt
pmorse.egg-info/dependency_links.txt
pmorse.egg-info/top_level.txt